Workbook

Sheet Exchange Ratio
A1: Exchange Ratio
A3: WDFC Price | B3: =DCF!C3 -> 190.73 | F3: This project attempted to answer the question as to how much COST should pay to aquire WDFC
A4: COST Price | B4: =DCF!B3 -> 894.77
B6: Exchange Ratio | C6: Price | D6: Premium %
A7: Relative Valuation | B7: ='Relative Valuation'!E28 -> 0.28557178 | C7: ='Relative Valuation'!C28 -> 255.52106 | D7: =(C7/B3)-1 -> 0.33970044
A8: Synergy Valuation | B8: =Synergies!J21 -> 0.26032791 | C8: =Synergies!J20 -> 232.9336 | D8: =(C8/B3)-1 -> 0.22127406
A9: DCF Valuation | B9: =DCF!F25/'Exchange Ratio'!B4 -> 0.13364432 | C9: =DCF!F25 -> 119.58093 | D9: =(C9/B3)-1 -> -0.37303554
A11: Offer Range | C11: 0.49
A12: $230-260

Sheet DCF
A1: Costco | B1: =TODAY() -> 46083 | C1: 1000000 | D1: =EDATE(B1,-0.05) -> 46083
B2: #VALUE! | C2: #VALUE!
A3: Share Price | B3: 894.77 | C3: 190.73
A4: Shares Outstanding | B4: =443.18*C1 -> 443180000 | C4: =13.53*C1 -> 13530000
A5: Debt | B5: =8173*C1 -> 8173000000 | C5: =94.6*C1 -> 94600000
A6: Cash | B6: =14161*C1 -> 14161000000 | C6: =58.1*C1 -> 58100000
A7: EV | B7: =396235.3*C1 -> 396235300000 | C7: =2702.1*C1 -> 2702100000
A8: Revenue | B8: =275235*C1 -> 275235000000 | C8: =620*C1 -> 620000000
A9: EBITDA | B9: =12809*C1 -> 12809000000 | C9: =112*C1 -> 112000000
A10: Net Income | B10: =7586*C1 -> 7586000000 | C10: =91*C1 -> 91000000
A11: Multiple | C11: 16.12
A12: Comps
A13: Ratios | B13: EV/EBITDA | C13: EV/Revenue | D13: P/E | G13: EV/Rev | H13: EV/EBITDA | I13: EV/EBIT | J13: P/E
A14: Costco | B14: 28.5 | C14: 1.34 | D14: 50.58 | F14: WD-40 COMPANY (XNAS:WDFC) | G14: 0.62 | H14: 2.67 | I14: 3.57 | J14: 7
A15: Walmart | B15: 22.27 | C15: 1.29 | D15: 43.41 | F15: QUAKER CHEMICAL CORPORATION (XNYS:KWR) | G15: 3.68 | H15: 19.56 | I15: 48.16 | J15: 102
A16: BJ's Wholesale Club | B16: 12.97 | C16: 0.64 | D16: 20.04 | F16: NEWELL BRANDS INC. (XNAS:NWL) | G16: 4.35 | H16: 21.9 | I16: 322.36 | J16: 106
A17: Target | B17: 6.98 | C17: 0.56 | D17: 12.12 | F17: Siemens Energy AG (XFRA:ENR) | G17: 24.24 | H17: -1022.5 | I17: -456.98 | J17: -783
A18: Amazon | B18: 16.89 | C18: 3.31 | D18: 34.98 | F18: CENTRAL GARDEN & PET COMPANY (XNAS:CENTA) | G18: 5.94 | H18: 70.05 | I18: 494.07 | J18: 803
A19: Kroger | B19: 8.95 | C19: 0.43 | D19: 14.97 | F19: Weighted Average | G19: 7.83 | H19: -128.9 | I19: 182.1 | J19: 186.2
A20: Averages | B20: =AVERAGE(B15:B19) -> 13.612 | C20: =AVERAGE(C15:C19) -> 1.246 | D20: =AVERAGE(D15:D19) -> 25.104 | F20: Price Range | G20: 1493.97 | H20: -5366.31 | I20: 5828.39 | J20: 5410.37
A23: WDFC | B23: 26.4 | C23: 4.19 | D23: 32.29
A24: Costco
A25: WDFC | B25: =((C11*$C$9)-$C$5+$C$6)/$C$4 -> 130.74205 | C25: =((C11*$C$8)-$C$5+$C$6)/$C$4 -> 735.9867 | D25: =(C10/C4)*C11 -> 108.41981 | F25: =AVERAGE(D25,B25) -> 119.58093
A26: COSTCO | B26: =((B20*$B$9)-$B$5+$B$6)/$B$4 -> 406.93196 | C26: =((C20*$B$8)-$B$5+$B$6)/$B$4 -> 787.33429 | D26: =(B10/B4)*D20 -> 429.71015
A27: Range | B27: $406.93 - $787.33

Sheet DCF Real
A1: WDFC Financials | B1: (Millions) | D1: Years | E1: 2022 | F1: 2023 | G1: 2024 | H1: 2025 | K1: 2022 | L1: 2023 | M1: 2024 | N1: 2025 | P1: wacc | Q1: 0.06639
A2: Revenue | B2: 619.99 | D2: Revenues | E2: 518.82 | F2: 537.26 | G2: 590.56 | H2: =B2 -> 619.99 | J2: Current Assets | K2: 249640 | L2: 248525 | M2: 255441 | N2: 284956
A3: EBIT | B3: 105.07 | D3: EBIT | E3: 86.85 | F3: 90.78 | G3: 95.8 | H3: =B3 -> 105.07 | J3: Current Liabilities | K3: 110820 | L3: 88842 | M3: 103500 | N3: 102257
A4: Net Income | B4: 90.73 | D4: FCFS | E4: -5.7 | F4: 91.52 | G4: 87.83 | H4: 83.4 | J4: NWC | K4: =K2-K3 -> 138820 | L4: =L2-L3 -> 159683 | M4: =M2-M3 -> 151941 | N4: =N2-N3 -> 182699
A5: Total Debt | B5: 97.7 | J5: Changes in NWC | K5: N/A | L5: =K4-L4 -> -20863 | M5: =L4-M4 -> 7742 | N5: =M4-N4 -> -30758
A6: Cash | B6: 58.13
A7: Working Cap | B7: 182.7 | D7: Line Item ($ Millions) | E7: 2025 (Base) | F7: 2026 (Yr 1) | G7: 2027 (Yr 2) | H7: 2028 (Yr 3) | I7: 2029 (Yr 4) | J7: 2030 (Yr 5)
A8: Depreciation | B8: 183 | D8: Revenue | E8: 619.99 | F8: 657.19 | G8: 696.62 | H8: 738.42 | I8: 782.72 | J8: 829.69
A9: Capex | B9: 4.53 | D9: Growth % | E9: - | F9: 0.06 | G9: 0.06 | H9: 0.06 | I9: 0.06 | J9: 0.06
A10: Changes in NWC | D10: EBIT (Operating Income) | E10: 105.07 | F10: 111.72 | G10: 118.43 | H10: 125.53 | I10: 133.06 | J10: 141.05
A11: Shares Outstanding | B11: ='Relative Valuation'!C20 -> 13.53 | D11: Margin % | E11: 0.17 | F11: 0.17 | G11: 0.17 | H11: 0.17 | I11: 0.17 | J11: 0.17
A12: Tax Rate | B12: 0.25 | D12: Less: Taxes (25%) | E12: 0.25 | F12: =$E$12 -> 0.25 | G12: =$E$12 -> 0.25 | H12: =$E$12 -> 0.25 | I12: =$E$12 -> 0.25 | J12: =$E$12 -> 0.25
A13: WACC | B13: 0.0837 | D13: NOPAT | E13: =E10-(E10*E12) -> 78.8025 | F13: =F10-(F10*F12) -> 83.79 | G13: =G10-(G10*G12) -> 88.8225 | H13: =H10-(H10*H12) -> 94.1475 | I13: =I10-(I10*I12) -> 99.795 | J13: =J10-(J10*J12) -> 105.7875
A14: Beta | B14: 0.16 | D14: Plus: D&A | E14: 8.19 | F14: =E14+(E14*$B$16) -> 8.6814 | G14: =F14+(F14*$B$16) -> 9.202284 | H14: =G14+(G14*$B$16) -> 9.754421 | I14: =H14+(H14*$B$16) -> 10.339686 | J14: =I14+(I14*$B$16) -> 10.960067
A15: Risk-Free Rate | B15: 0.04597 | D15: Less: CapEx | E15: =-B9 -> -4.53 | F15: =E15+(E15*B$16) -> -4.8018 | G15: =F15+(F15*$B$16) -> -5.089908 | H15: =G15+(G15*$B$16) -> -5.3953025 | I15: =H15+(H15*$B$16) -> -5.7190206 | J15: =I15+(I15*$B$16) -> -6.0621619
A16: Growth Rate | B16: 0.06
A17: Share Price | B17: =DCF!C3 -> 190.73 | D17: Unlevered FCF | E17: =E13+E14+E15+E16 -> 82.4625 | F17: =F13+F14+F15+F16 -> 87.6696 | G17: =G13+G14+G15+G16 -> 92.934876 | H17: =H13+H14+H15+H16 -> 98.506619 | I17: =I13+I14+I15+I16 -> 104.41567 | J17: =J13+J14+J15+J16 -> 110.68541
F20: Years | G20: 2025 | H20: 2026 | I20: 2027 | J20: 2028 | K20: 2029 | L20: 2030
F21: FCFs | G21: 86 | H21: 80 | I21: 83 | J21: 109 | K21: 111 | L21: 114 | M21: 119
F22: =NPV(Q1,G21:M21) -> 537.61581
E26: =3495/'Relative Valuation'!C20 -> 258.31486

Sheet Relative Valuation
A1: Relative Valuation
B3: Psychological Factor | C3: 289 | D3: 52 Week High
B4: Premium | C4: =C3/'ER Current Market'!B3-1 -> 0.51523095
B5: Premium Value | C5: =C23*C4 -> 1.3292959
B6: Implied Acquisition EV | C6: =C5+C23 -> 3.9092959
B7: Equity Value per Share | C7: =C6/C20*1000 -> 288.93539
B9: Precedent Transactions | D9: WD-40 is not a generic soap brand, it has the pricing power of its market
B10: from consumer sector: | D10: should be compared to loyalty cult brands
B12: Power Brand | C12: Premium | D12: Valuation Multiple
B13: Mars buy Kellanova | C13: 0.44 | D13: 16.4
B14: Campbells buys Sovos | C14: 0.28 | D14: 19.8 | E14: should be compared to loyalty cult brands
B15: Perrigo buys HR Pharma | C15: 0.38 | D15: 18.4
B16: SC Johnson buys Method & Ecover | C16: 0.4 | D16: 18 | J16: Premium Average | K16: 0.34
B17: Stanley Black and Decker buys MTD | C17: 0.2 | D17: 8 | J17: WDFC Price | K17: =C22 -> 190.73
B18: Averages | C18: =(C13+C14+C15+C16+C17)/5 -> 0.34 | D18: =(D13+D14+D15+D16+D17)/5 -> 16.12 | J18: Premium Valuation | K18: =(K16+1)*K17 -> 255.5782
B20: WDFC Shares outstanding (Millions) | C20: 13.53
B21: Costco Price | C21: =DCF!B3 -> 894.77
B22: WDFC Price | C22: =DCF!C3 -> 190.73 | D22: 190.73
B23: WDFC Market Cap (In Billions) | C23: 2.58
B24: WDFC EBITDA (In Millions) | C24: 113.26
B25: Implied EV = EBITDA x Peer Multiple | C25: =C24*D18 -> 1825.7512
B26: Premium Value | C26: =C23*C18 -> 0.8772
B27: Implied Acquisition EV | C27: =C26+C23 -> 3.4572 | E27: Ratio
B28: Equity Value per Share | C28: =C27/C20*1000 -> 255.52106 | E28: =C28/DCF!B3 -> 0.28557178
B30: Price Range | C30: Per Share
B31: Base Valuation | C31: $190-200
B32: Comps Valuation | C32: $250-260
B33: 52 Week High Valuation | C33: $275-285
B35: Aquisition Price | C35: 260
B36: Total Aquisition Cost (Millions) | C36: =C35*C20 -> 3517.8

Sheet Synergies
B1: All savings % are based from M&A integration studies, industry reports, and case examples.
K2: ='Valuation Multplier'!C6 -> 22.727273 | L2: x
I3: Synergy Item | J3: Annual Value | K3: Valuation muliplier (WACC) | L3: Value Creation (WACC)
B4: Raw Exchange ratio | C4: ='ER Current Market'!B4 -> 0.21316092 | E4: Min exchange | I4: Marketing | J4: =C11 -> 23800000 | K4: =$K$2 -> 22.727273 | L4: =PRODUCT(J4:K4) -> 5.4090909e+08
I5: Supply Chain | J5: =C17 -> 11702964 | K5: =$K$2 -> 22.727273 | L5: =PRODUCT(J5:K5) -> 2.6597645e+08
I6: Public Costs | J6: =C20 -> 5000000 | K6: =$K$2 -> 22.727273 | L6: =PRODUCT(J6:K6) -> 1.1363636e+08
A7: Synergies | I7: Debt | J7: =C29 -> 1500000 | K7: =$K$2 -> 22.727273 | L7: =PRODUCT(J7:K7) -> 34090909
B8: Marketing: | I8: Manufacturing Fees | J8: =C34 -> 4179630 | K8: =$K$2 -> 22.727273 | L8: =PRODUCT(J8:K8) -> 94991591
B9: WDFC marketing | C9: 34000000 | I9: Packaging | J9: =C40 -> 2966701.4 | K9: =$K$2 -> 22.727273 | L9: =PRODUCT(J9:K9) -> 67425031
B10: Est savings % | C10: 0.7 | D10: of budget, costco spends very little on ads | I10: WC release | J10: =C25 -> 25000000 | K10: na | L10: =PRODUCT(J10:K10) -> 25000000
B11: annual saving | C11: =C10*C9 -> 23800000 | L11: =SUM(L4:L10) -> 1.1420294e+09
B13: Supply Chain | I13: WDFC Market Cap | J13: =J18*DCF!C3 -> 2580576900
B14: WDFC COGS | C14: 278642000 | I14: Synergy Value | J14: =L11 -> 1.1420294e+09
B15: Est Logistics cost % | C15: 0.14 | D15: of COGS is logistics | I15: Max value to COSTCO | J15: =SUM(J13:J14) -> 3.7226063e+09
B16: Est savings % | C16: 0.3 | D16: once transferrd to COST logistics | I16: Max Exchange Ratio | J16: =J15/J18 -> 275.1372
B17: Annual Savings | C17: =(C14*C15)*C16 -> 11702964 | D17: COST sys moves good directly from manufacturer to store, bypassing storage
I18: WDFC Shares | J18: =DCF!C4 -> 13530000
B19: Public company cost | C19: 5000000 | D19: Removed | I19: Sharing of synergies% | J19: 0.5
B20: Annual Savings | C20: =C19 -> 5000000 | I20: Target Share Price | J20: =(J13+J14*J19)/J18 -> 232.9336
I21: Preffered Exchange ratio | J21: =J20/DCF!B3 -> 0.26032791
B22: Working Cap release
B23: WDFC A/R | C23: 125000000 | D23: 30-60 day payment | I23: WDFC Aquisition Price | J23: 3518000000
B24: Est one-time payout % | C24: 0.2 | D24: because COST gets paid instantly at the register and pays suppliers instantly so it has a negative WC. | I24: Max Value to COSTCO | J24: =J15 -> 3.7226063e+09
B25: Est one-time payout | C25: =C23*C24 -> 25000000 | D25: This would make recievables efficient and open up cash | I25: Return on Investment | J25: =J24-J23 -> 2.0460634e+08
B27: Debt
B28: WDFC Debt | C28: 87000000
B29: Annual Savings | C29: 1500000 | D29: COST has a AA rating and will get better rates
B31: Manufacturing fees
B32: WDFC Manufacturing fees | C32: =0.3*C14 -> 83592600 | D32: WDFC spends on a third party mixing and filling cans
B33: Man fees savings % | C33: 0.05 | D33: COST guarantees massive, consistent volume that removes volatility.
B34: Annual Savings | C34: =C32*C33 -> 4179630 | D34: COST will renegotiate fees
B36: Tin-Plate & Plastic Procurement
B37: Procurement Cost | C37: =0.39*C14 -> 108670380
B38: Packaging Cost | C38: =0.39*C37 -> 42381448 | D38: COST leader in buying packaging, prices for them will go down
B39: Annual Savings % | C39: 0.07
B40: Annual Savings | C40: =C38*C39 -> 2966701.4

Sheet Valuation Multplier
B2: Perpetuity
B3: WDFC WACC | C3: ='Discount Rate'!F3 -> 0.064
B4: GDP Growth | C4: 0.02
B6: Valuation Multiple | C6: =1/(C3-C4) -> 22.727273
B11: Market
B12: COST P/E | C12: =DCF!D14 -> 50.58
B13: WDFC P/E | C13: =DCF!D23 -> 32.29
B14: Consumer Stapes P/E | C14: 18.5

Sheet ER Current Market
A1: Exchange Ratio Based on Current Market Price | D1: if we payed zero premium
A2: COST Price | B2: =DCF!B3 -> 894.77
A3: WDFC Price | B3: =DCF!C3 -> 190.73
A4: Floor Cost of WDFC's shares | B4: =B3/B2 -> 0.21316092 | C4: COST shares for WDFC

Sheet Discount Rate
B2: Rf | E2: WACC
B3: US 10Y | C3: 0.04088 | E3: WDFC | F3: 0.064 | N3: WDFC | O3: COST
B4: US 3M | C4: 0.0388 | E4: COST | F4: 0.085 | M4: EV | N4: 2702100000 | O4: 396235300000
L5: DDM | M5: Implied Return | O5: 0.05986
M6: Implied GR | O6: 0.19974
M7: Expected Market Return | O7: 0.10249
M8: Beta | O8: 0.727

Sheet Reverse Engineering DR
B2: COST | I2: WDFC
C3: Price | D3: {=_xll.BDP("COST US Equity", "PX_LAST")} -> #NAME? | E3: 919.415 | J3: Price | K3: {=_xll.BDP("COST US Equity", "PX_LAST")} -> #NAME? | L3: 196.63
C4: Y1 | D4: {=_xll.BDP("COST US Equity","BEST_EPS","BEST_FPERIOD_OVERRIDE", "1FY")} -> #NAME? | E4: 20.075 | J4: Y1 | K4: {=_xll.BDP("COST US Equity","BEST_EPS","BEST_FPERIOD_OVERRIDE", "1FY")} -> #NAME? | L4: 6.075
C5: Y2 | D5: {=_xll.BDP("COST US Equity","BEST_EPS","BEST_FPERIOD_OVERRIDE", "2FY")} -> #NAME? | E5: 22.096 | J5: Y2 | K5: {=_xll.BDP("COST US Equity","BEST_EPS","BEST_FPERIOD_OVERRIDE", "2FY")} -> #NAME? | L5: 6.535
C6: Y3 | D6: {=_xll.BDP("COST US Equity","BEST_EPS","BEST_FPERIOD_OVERRIDE", "3FY")} -> #NAME? | E6: 24.417 | J6: Y3 | K6: {=_xll.BDP("COST US Equity","BEST_EPS","BEST_FPERIOD_OVERRIDE", "3FY")} -> #NAME? | L6: 7.35
C8: Implied Rate | D8: 0.09 | E8: 0.050152171 | J8: Implied Rate | K8: 0.09 | L8: 0.060321102
C9: growth | E9: =0.025 -> 0.025 | J9: growth | L9: =0.025 -> 0.025
C11: Y1 | D11: Y2 | E11: Y3 | F11: Terminal | J11: Y1 | K11: Y2 | L11: Y3 | M11: Terminal
B12: CF | C12: =E4 -> 20.075 | D12: =E5 -> 22.096 | E12: =E6 -> 24.417 | F12: =E6*(1+E9) -> 25.027425 | I12: CF | J12: =L4 -> 6.075 | K12: =L5 -> 6.535 | L12: =L6 -> 7.35 | M12: =L6*(1+L9) -> 7.53375
B13: Discount Factor | C13: =(1+$E$8)^1 -> 1.0501522 | D13: =(1+$E$8)^2 -> 1.1028196 | E13: =(1+$E$8)^3 -> 1.1581284 | F13: =(1+$E$8)^3 -> 1.1581284 | I13: Discount Factor | J13: =(1+$L$8)^1 -> 1.0603211 | K13: =(1+$L$8)^2 -> 1.1242808 | L13: =(1+$L$8)^3 -> 1.1920987 | M13: =(1+$L$8)^3 -> 1.1920987
B14: PV | C14: =C12/C13 -> 19.116277 | D14: =D12/D13 -> 20.035916 | E14: =E12/E13 -> 21.083155 | F14: =F12/F13 -> 21.610234 | I14: PV | J14: =J12/J13 -> 5.7293965 | K14: =K12/K13 -> 5.8126046 | L14: =L12/L13 -> 6.1655969 | M14: =M12/M13 -> 6.3197368
B17: Gordan Growth Formula | I17: Gordan Growth Formula
B18: Terminal Value | C18: =F12/(E8-E9) -> 995.04034 | I18: Terminal Value | J18: =M12/(L8-L9) -> 213.29318
B19: PV TV | C19: =C18/(1+E8)^3 -> 859.17965 | I19: PV TV | J19: =J18/(1+L8)^3 -> 178.92241
B21: Total Value | C21: =SUM(C14:E14,C19) -> 919.415 | I21: Total Value | J21: =SUM(J14:L14,J19) -> 196.63001
B23: What-if-analysis> goal seek>C21 set to stock price, changing implied rate
B25: implied rate | C25: =E8 -> 0.050152171 | D25: This is the cost of equity from the market | I25: implied rate | J25: =L8 -> 0.060321102 | K25: This is the cost of equity from the market
